auacm/__init__.py
auacm/common.py
auacm/competition.py
auacm/exceptions.py
auacm/main.py
auacm/problems.py
auacm/submit.py
auacm/user.py
auacm/utils.py
auacm-0.4.data/scripts/auacm
auacm-0.4.dist-info/DESCRIPTION.rst
auacm-0.4.dist-info/METADATA
auacm-0.4.dist-info/RECORD
auacm-0.4.dist-info/WHEEL
auacm-0.4.dist-info/metadata.json
auacm-0.4.dist-info/top_level.txt
