Metadata-Version: 2.0
Name: auacm
Version: 0.4
Summary: A command line interface to the Auburn ACM website
Home-page: https://github.com/BrandonLMorris/auacm-cli
Author: Brandon Morris
Author-email: brandon.morris95@gmail.com
License: MIT
Download-URL: https://github.com/BrandonLMorris/auacm-cli/tarball/0.4
Keywords: competitive,icpc,auacm,auburn
Platform: UNKNOWN
Classifier: License :: OSI Approved :: MIT License
Classifier: Programming Language :: Python
Classifier: Programming Language :: Python :: 3.5
Classifier: Programming Language :: Python :: 3.4
Requires-Dist: requests
